alkaid-0.0.1a0.dist-info/RECORD
alkaid-0.0.1a0.dist-info/WHEEL
alkaid-0.0.1a0.dist-info/entry_points.txt
alkaid-0.0.1a0.dist-info/METADATA
da4ml/_version.py
da4ml/__init__.py
da4ml/_binary/dais_bin.pyi
da4ml/_binary/__init__.py
da4ml/_binary/dais_bin.cpython-312-darwin.so
da4ml/trace/__init__.py
da4ml/trace/fixed_variable.py
da4ml/trace/fixed_variable_array.py
da4ml/trace/pipeline.py
da4ml/trace/tracer.py
da4ml/trace/ops/reduce_utils.py
da4ml/trace/ops/quantization.py
da4ml/trace/ops/__init__.py
da4ml/trace/ops/einsum_utils.py
da4ml/converter/__init__.py
da4ml/converter/hgq2/__init__.py
da4ml/converter/hgq2/parser.py
da4ml/converter/hgq2/layers/_base.py
da4ml/converter/hgq2/layers/batchnorm.py
da4ml/converter/hgq2/layers/dense.py
da4ml/converter/hgq2/layers/__init__.py
da4ml/converter/hgq2/layers/ops.py
da4ml/converter/hgq2/layers/activation.py
da4ml/converter/hgq2/layers/table.py
da4ml/converter/hgq2/layers/conv.py
da4ml/converter/hgq2/layers/pool.py
da4ml/converter/hgq2/layers/attn.py
da4ml/codegen/__init__.py
da4ml/codegen/hls/hls_model.py
da4ml/codegen/hls/__init__.py
da4ml/codegen/hls/hls_codegen.py
da4ml/codegen/hls/source/vitis_bitshift.hh
da4ml/codegen/hls/source/build_binder.mk
da4ml/codegen/hls/source/binder_util.hh
da4ml/codegen/hls/source/ap_types/ap_binary.h
da4ml/codegen/hls/source/ap_types/ap_fixed_ref.h
da4ml/codegen/hls/source/ap_types/ap_shift_reg.h
da4ml/codegen/hls/source/ap_types/ap_decl.h
da4ml/codegen/hls/source/ap_types/ap_int_special.h
da4ml/codegen/hls/source/ap_types/ap_fixed_special.h
da4ml/codegen/hls/source/ap_types/ap_int_base.h
da4ml/codegen/hls/source/ap_types/ap_common.h
da4ml/codegen/hls/source/ap_types/ap_fixed.h
da4ml/codegen/hls/source/ap_types/ap_fixed_base.h
da4ml/codegen/hls/source/ap_types/ap_int_ref.h
da4ml/codegen/hls/source/ap_types/ap_int.h
da4ml/codegen/hls/source/ap_types/hls_stream.h
da4ml/codegen/hls/source/ap_types/hls_math.h
da4ml/codegen/hls/source/ap_types/etc/ap_private.h
da4ml/codegen/hls/source/ap_types/utils/x_hls_utils.h
da4ml/codegen/rtl/__init__.py
da4ml/codegen/rtl/rtl_model.py
